LICENSE
silex/__init__.py
silex/df.py
silex/exception.py
silex/fn/__init__.py
silex/fn/date.py
silex/fn/drop.py
silex/fn/expect.py
silex/fn/filter.py
silex/fn/has.py
silex/fn/join.py
silex/testing/__init__.py
silex/testing/spark.py
silex/testing/string.py
silex/utils/__init__.py
silex/utils/spark.py
spark_silex-0.2.0.dist-info/LICENSE
spark_silex-0.2.0.dist-info/WHEEL
spark_silex-0.2.0.dist-info/METADATA
spark_silex-0.2.0.dist-info/RECORD
