Metadata-Version: 2.1
Name: spark-silex
Version: 0.2.0
Summary: Silex adds more sparks to your project!
Home-page: https://github.com/RickCi/silex
License: MIT
Keywords: spark,dataframe
Author: RickCi
Author-email: rci-git@pm.me
Requires-Python: >=3.8,<4
Classifier: Development Status :: 4 - Beta
Classifier: Environment :: Console
Classifier: Intended Audience :: Developers
Classifier: License :: OSI Approved :: MIT License
Classifier: Operating System :: OS Independent
Classifier: Programming Language :: Python :: 3
Classifier: Programming Language :: Python :: 3.8
Classifier: Programming Language :: Python :: 3.9
Classifier: Programming Language :: Python :: 3.10
Classifier: Topic :: Software Development :: Libraries :: Python Modules
Requires-Dist: pyspark (>=3)
Project-URL: Changelog, https://github.com/RickCi/silex/blob/master/CHANGELOG.md
Project-URL: Repository, https://github.com/RickCi/silex
